README.txt
setup.cfg
setup.py
docs/HISTORY.txt
raptus/__init__.py
raptus.mercurialstorage.egg-info/PKG-INFO
raptus.mercurialstorage.egg-info/SOURCES.txt
raptus.mercurialstorage.egg-info/dependency_links.txt
raptus.mercurialstorage.egg-info/entry_points.txt
raptus.mercurialstorage.egg-info/namespace_packages.txt
raptus.mercurialstorage.egg-info/not-zip-safe
raptus.mercurialstorage.egg-info/requires.txt
raptus.mercurialstorage.egg-info/top_level.txt
raptus/mercurialstorage/__init__.py
raptus/mercurialstorage/configure.zcml
raptus/mercurialstorage/datamanager.py
raptus/mercurialstorage/download.py
raptus/mercurialstorage/es.patch
raptus/mercurialstorage/interfaces.py
raptus/mercurialstorage/logger.py
raptus/mercurialstorage/queue.py
raptus/mercurialstorage/storage.py
raptus/mercurialstorage/version.txt