Metadata-Version: 1.0
Name: raptus.mercurialstorage
Version: 0.4
Summary: provides an archetypes storage which stores files on the filesystem into a mercurial repository
Home-page: http://plone.org/products/raptus.mercurialstorage
Author: Raptus AG
Author-email: skaeser@raptus.com
License: GPL
Keywords: plone archetypes storage mercurial
Platform: UNKNOWN
Classifier: Framework :: Plone
Classifier: Programming Language :: Python
Classifier: Topic :: Software Development :: Libraries :: Python Modules
